{
  "schema_version": 1,
  "meta": {
    "updated": "2026-03-01",
    "note": "CPI/賃上げ率は必要に応じて追記。最低賃金は厚労省の答申状況（発効日予定）に基づく。",
    "sources": {
      "min_wage": {
        "publisher": "厚生労働省",
        "title": "令和7年度 地域別最低賃金 答申状況（別紙）",
        "url": "https://www.mhlw.go.jp/content/11302000/001557056.pdf",
        "caution": "発効日（予定）は異議申出等により変更となる可能性あり。"
      },
      "min_wage_history_excel": {
        "publisher": "（不明：添付Excel）",
        "title": "001571219 (1).xlsx / シート「H14～R７」",
        "caution": "本チャットにアップロードされたExcelから、各年度の『改定額(円)』を転記。都道府県名はExcel表記の空白を除去して正規化。"
      }
    }
  },
  "national": {
    "cpi_yoy": 2,
    "cpi_asof": "2026年1月（前年同月比・生鮮食品を除く総合）",
    "wage_yoy": 4.65,
    "wage_asof": "2025年春季生活闘争（連合 第7回〔最終〕回答集計：300人未満の中小組合・加重平均）",
    "sources": {
      "cpi": "e-Stat（総務省統計局）『2026年1月分 消費者物価指数（CPI）結果の概要（全国）』",
      "wage": "連合『2025春季生活闘争 第7回（最終）回答集計結果について』（2025-07-03）"
    },
    "min_wage_avg": {
      "new": 1121,
      "old": 1055,
      "inc": 66,
      "eff": null
    },
    "min_wage_history_avg": {
      "2002": 663,
      "2003": 664,
      "2004": 665,
      "2005": 668,
      "2006": 673,
      "2007": 687,
      "2008": 703,
      "2009": 713,
      "2010": 730,
      "2011": 737,
      "2012": 749,
      "2013": 764,
      "2014": 780,
      "2015": 798,
      "2016": 823,
      "2017": 847,
      "2018": 874,
      "2019": 901,
      "2020": 902,
      "2021": 930,
      "2022": 961,
      "2023": 1004,
      "2024": 1055,
      "2025": 1121
    },
    "min_wage_by_pref": {
      "北海道": {
        "new": 1075,
        "old": 1010,
        "inc": 65,
        "eff": "2025-10-04"
      },
      "青森": {
        "new": 1029,
        "old": 953,
        "inc": 76,
        "eff": "2025-11-21"
      },
      "岩手": {
        "new": 1031,
        "old": 952,
        "inc": 79,
        "eff": "2025-12-01"
      },
      "宮城": {
        "new": 1038,
        "old": 973,
        "inc": 65,
        "eff": "2025-10-04"
      },
      "秋田": {
        "new": 1031,
        "old": 951,
        "inc": 80,
        "eff": "2026-03-31"
      },
      "山形": {
        "new": 1032,
        "old": 955,
        "inc": 77,
        "eff": "2025-12-23"
      },
      "福島": {
        "new": 1033,
        "old": 955,
        "inc": 78,
        "eff": "2026-01-01"
      },
      "茨城": {
        "new": 1074,
        "old": 1005,
        "inc": 69,
        "eff": "2025-10-12"
      },
      "栃木": {
        "new": 1068,
        "old": 1004,
        "inc": 64,
        "eff": "2025-10-01"
      },
      "群馬": {
        "new": 1063,
        "old": 985,
        "inc": 78,
        "eff": "2026-03-01"
      },
      "埼玉": {
        "new": 1141,
        "old": 1078,
        "inc": 63,
        "eff": "2025-11-01"
      },
      "千葉": {
        "new": 1140,
        "old": 1076,
        "inc": 64,
        "eff": "2025-10-03"
      },
      "東京": {
        "new": 1226,
        "old": 1163,
        "inc": 63,
        "eff": "2025-10-03"
      },
      "神奈川": {
        "new": 1225,
        "old": 1162,
        "inc": 63,
        "eff": "2025-10-04"
      },
      "新潟": {
        "new": 1050,
        "old": 985,
        "inc": 65,
        "eff": "2025-10-02"
      },
      "富山": {
        "new": 1062,
        "old": 998,
        "inc": 64,
        "eff": "2025-10-12"
      },
      "石川": {
        "new": 1054,
        "old": 984,
        "inc": 70,
        "eff": "2025-10-08"
      },
      "福井": {
        "new": 1053,
        "old": 984,
        "inc": 69,
        "eff": "2025-10-08"
      },
      "山梨": {
        "new": 1052,
        "old": 988,
        "inc": 64,
        "eff": "2025-12-01"
      },
      "長野": {
        "new": 1061,
        "old": 998,
        "inc": 63,
        "eff": "2025-10-03"
      },
      "岐阜": {
        "new": 1065,
        "old": 1001,
        "inc": 64,
        "eff": "2025-10-18"
      },
      "静岡": {
        "new": 1097,
        "old": 1034,
        "inc": 63,
        "eff": "2025-11-01"
      },
      "愛知": {
        "new": 1140,
        "old": 1077,
        "inc": 63,
        "eff": "2025-10-18"
      },
      "三重": {
        "new": 1087,
        "old": 1023,
        "inc": 64,
        "eff": "2025-11-21"
      },
      "滋賀": {
        "new": 1080,
        "old": 1017,
        "inc": 63,
        "eff": "2025-10-05"
      },
      "京都": {
        "new": 1122,
        "old": 1058,
        "inc": 64,
        "eff": "2025-11-21"
      },
      "大阪": {
        "new": 1177,
        "old": 1114,
        "inc": 63,
        "eff": "2025-10-16"
      },
      "兵庫": {
        "new": 1116,
        "old": 1052,
        "inc": 64,
        "eff": "2025-10-04"
      },
      "奈良": {
        "new": 1051,
        "old": 986,
        "inc": 65,
        "eff": "2025-11-16"
      },
      "和歌山": {
        "new": 1045,
        "old": 980,
        "inc": 65,
        "eff": "2025-11-01"
      },
      "鳥取": {
        "new": 1030,
        "old": 957,
        "inc": 73,
        "eff": "2025-10-04"
      },
      "島根": {
        "new": 1033,
        "old": 962,
        "inc": 71,
        "eff": "2025-11-17"
      },
      "岡山": {
        "new": 1047,
        "old": 982,
        "inc": 65,
        "eff": "2025-12-01"
      },
      "広島": {
        "new": 1085,
        "old": 1020,
        "inc": 65,
        "eff": "2025-11-01"
      },
      "山口": {
        "new": 1043,
        "old": 979,
        "inc": 64,
        "eff": "2025-10-16"
      },
      "徳島": {
        "new": 1046,
        "old": 980,
        "inc": 66,
        "eff": "2026-01-01"
      },
      "香川": {
        "new": 1036,
        "old": 970,
        "inc": 66,
        "eff": "2025-10-18"
      },
      "愛媛": {
        "new": 1033,
        "old": 956,
        "inc": 77,
        "eff": "2025-12-01"
      },
      "高知": {
        "new": 1023,
        "old": 952,
        "inc": 71,
        "eff": "2025-12-01"
      },
      "福岡": {
        "new": 1057,
        "old": 992,
        "inc": 65,
        "eff": "2025-11-16"
      },
      "佐賀": {
        "new": 1030,
        "old": 956,
        "inc": 74,
        "eff": "2025-11-21"
      },
      "長崎": {
        "new": 1031,
        "old": 953,
        "inc": 78,
        "eff": "2025-12-01"
      },
      "熊本": {
        "new": 1034,
        "old": 952,
        "inc": 82,
        "eff": "2026-01-01"
      },
      "大分": {
        "new": 1035,
        "old": 954,
        "inc": 81,
        "eff": "2026-01-01"
      },
      "宮崎": {
        "new": 1023,
        "old": 952,
        "inc": 71,
        "eff": "2025-11-16"
      },
      "鹿児島": {
        "new": 1026,
        "old": 953,
        "inc": 73,
        "eff": "2025-11-01"
      },
      "沖縄": {
        "new": 1023,
        "old": 952,
        "inc": 71,
        "eff": "2025-12-01"
      }
    },
    "min_wage_history_by_pref": {
      "三重": {
        "2002": 667,
        "2003": 667,
        "2004": 668,
        "2005": 671,
        "2006": 675,
        "2007": 689,
        "2008": 701,
        "2009": 702,
        "2010": 714,
        "2011": 717,
        "2012": 724,
        "2013": 737,
        "2014": 753,
        "2015": 771,
        "2016": 795,
        "2017": 820,
        "2018": 846,
        "2019": 873,
        "2020": 874,
        "2021": 902,
        "2022": 933,
        "2023": 973,
        "2024": 1023,
        "2025": 1087
      },
      "京都": {
        "2002": 677,
        "2003": 677,
        "2004": 678,
        "2005": 682,
        "2006": 686,
        "2007": 700,
        "2008": 717,
        "2009": 729,
        "2010": 749,
        "2011": 751,
        "2012": 759,
        "2013": 773,
        "2014": 789,
        "2015": 807,
        "2016": 831,
        "2017": 856,
        "2018": 882,
        "2019": 909,
        "2020": 909,
        "2021": 937,
        "2022": 968,
        "2023": 1008,
        "2024": 1058,
        "2025": 1122
      },
      "佐賀": {
        "2002": 605,
        "2003": 605,
        "2004": 606,
        "2005": 608,
        "2006": 611,
        "2007": 619,
        "2008": 628,
        "2009": 629,
        "2010": 642,
        "2011": 646,
        "2012": 653,
        "2013": 664,
        "2014": 678,
        "2015": 694,
        "2016": 715,
        "2017": 737,
        "2018": 762,
        "2019": 790,
        "2020": 792,
        "2021": 821,
        "2022": 853,
        "2023": 900,
        "2024": 956,
        "2025": 1030
      },
      "兵庫": {
        "2002": 675,
        "2003": 675,
        "2004": 676,
        "2005": 679,
        "2006": 683,
        "2007": 697,
        "2008": 712,
        "2009": 721,
        "2010": 734,
        "2011": 739,
        "2012": 749,
        "2013": 761,
        "2014": 776,
        "2015": 794,
        "2016": 819,
        "2017": 844,
        "2018": 871,
        "2019": 899,
        "2020": 900,
        "2021": 928,
        "2022": 960,
        "2023": 1001,
        "2024": 1052,
        "2025": 1116
      },
      "北海道": {
        "2002": 637,
        "2003": 637,
        "2004": 638,
        "2005": 641,
        "2006": 644,
        "2007": 654,
        "2008": 667,
        "2009": 678,
        "2010": 691,
        "2011": 705,
        "2012": 719,
        "2013": 734,
        "2014": 748,
        "2015": 764,
        "2016": 786,
        "2017": 810,
        "2018": 835,
        "2019": 861,
        "2020": 861,
        "2021": 889,
        "2022": 920,
        "2023": 960,
        "2024": 1010,
        "2025": 1075
      },
      "千葉": {
        "2002": 677,
        "2003": 677,
        "2004": 678,
        "2005": 682,
        "2006": 687,
        "2007": 706,
        "2008": 723,
        "2009": 728,
        "2010": 744,
        "2011": 748,
        "2012": 756,
        "2013": 777,
        "2014": 798,
        "2015": 817,
        "2016": 842,
        "2017": 868,
        "2018": 895,
        "2019": 923,
        "2020": 925,
        "2021": 953,
        "2022": 984,
        "2023": 1026,
        "2024": 1076,
        "2025": 1140
      },
      "和歌山": {
        "2002": 645,
        "2003": 645,
        "2004": 645,
        "2005": 649,
        "2006": 652,
        "2007": 662,
        "2008": 673,
        "2009": 674,
        "2010": 684,
        "2011": 685,
        "2012": 690,
        "2013": 701,
        "2014": 715,
        "2015": 731,
        "2016": 753,
        "2017": 777,
        "2018": 803,
        "2019": 830,
        "2020": 831,
        "2021": 859,
        "2022": 889,
        "2023": 929,
        "2024": 980,
        "2025": 1045
      },
      "埼玉": {
        "2002": 678,
        "2003": 678,
        "2004": 679,
        "2005": 682,
        "2006": 687,
        "2007": 702,
        "2008": 722,
        "2009": 735,
        "2010": 750,
        "2011": 759,
        "2012": 771,
        "2013": 785,
        "2014": 802,
        "2015": 820,
        "2016": 845,
        "2017": 871,
        "2018": 898,
        "2019": 926,
        "2020": 928,
        "2021": 956,
        "2022": 987,
        "2023": 1028,
        "2024": 1078,
        "2025": 1141
      },
      "大分": {
        "2002": 606,
        "2003": 606,
        "2004": 607,
        "2005": 610,
        "2006": 613,
        "2007": 620,
        "2008": 630,
        "2009": 631,
        "2010": 643,
        "2011": 647,
        "2012": 653,
        "2013": 664,
        "2014": 677,
        "2015": 694,
        "2016": 715,
        "2017": 737,
        "2018": 762,
        "2019": 790,
        "2020": 792,
        "2021": 822,
        "2022": 854,
        "2023": 899,
        "2024": 954,
        "2025": 1035
      },
      "大阪": {
        "2002": 703,
        "2003": 703,
        "2004": 704,
        "2005": 708,
        "2006": 712,
        "2007": 731,
        "2008": 748,
        "2009": 762,
        "2010": 779,
        "2011": 786,
        "2012": 800,
        "2013": 819,
        "2014": 838,
        "2015": 858,
        "2016": 883,
        "2017": 909,
        "2018": 936,
        "2019": 964,
        "2020": 964,
        "2021": 992,
        "2022": 1023,
        "2023": 1064,
        "2024": 1114,
        "2025": 1177
      },
      "奈良": {
        "2002": 647,
        "2003": 647,
        "2004": 648,
        "2005": 652,
        "2006": 656,
        "2007": 667,
        "2008": 678,
        "2009": 679,
        "2010": 691,
        "2011": 693,
        "2012": 699,
        "2013": 710,
        "2014": 724,
        "2015": 740,
        "2016": 762,
        "2017": 786,
        "2018": 811,
        "2019": 837,
        "2020": 838,
        "2021": 866,
        "2022": 896,
        "2023": 936,
        "2024": 986,
        "2025": 1051
      },
      "宮城": {
        "2002": 617,
        "2003": 617,
        "2004": 619,
        "2005": 623,
        "2006": 628,
        "2007": 639,
        "2008": 653,
        "2009": 662,
        "2010": 674,
        "2011": 675,
        "2012": 685,
        "2013": 696,
        "2014": 710,
        "2015": 726,
        "2016": 748,
        "2017": 772,
        "2018": 798,
        "2019": 824,
        "2020": 825,
        "2021": 853,
        "2022": 883,
        "2023": 923,
        "2024": 973,
        "2025": 1038
      },
      "宮崎": {
        "2002": 605,
        "2003": 605,
        "2004": 606,
        "2005": 608,
        "2006": 611,
        "2007": 619,
        "2008": 627,
        "2009": 629,
        "2010": 642,
        "2011": 646,
        "2012": 653,
        "2013": 664,
        "2014": 677,
        "2015": 693,
        "2016": 714,
        "2017": 737,
        "2018": 762,
        "2019": 790,
        "2020": 793,
        "2021": 821,
        "2022": 853,
        "2023": 897,
        "2024": 952,
        "2025": 1023
      },
      "富山": {
        "2002": 644,
        "2003": 644,
        "2004": 644,
        "2005": 648,
        "2006": 652,
        "2007": 666,
        "2008": 677,
        "2009": 679,
        "2010": 691,
        "2011": 692,
        "2012": 700,
        "2013": 712,
        "2014": 728,
        "2015": 746,
        "2016": 770,
        "2017": 795,
        "2018": 821,
        "2019": 848,
        "2020": 849,
        "2021": 877,
        "2022": 908,
        "2023": 948,
        "2024": 998,
        "2025": 1062
      },
      "山口": {
        "2002": 637,
        "2003": 637,
        "2004": 638,
        "2005": 642,
        "2006": 646,
        "2007": 657,
        "2008": 668,
        "2009": 669,
        "2010": 681,
        "2011": 684,
        "2012": 690,
        "2013": 701,
        "2014": 715,
        "2015": 731,
        "2016": 753,
        "2017": 777,
        "2018": 802,
        "2019": 829,
        "2020": 829,
        "2021": 857,
        "2022": 888,
        "2023": 928,
        "2024": 979,
        "2025": 1043
      },
      "山形": {
        "2002": 605,
        "2003": 606,
        "2004": 607,
        "2005": 610,
        "2006": 613,
        "2007": 620,
        "2008": 629,
        "2009": 631,
        "2010": 645,
        "2011": 647,
        "2012": 654,
        "2013": 665,
        "2014": 680,
        "2015": 696,
        "2016": 717,
        "2017": 739,
        "2018": 763,
        "2019": 790,
        "2020": 793,
        "2021": 822,
        "2022": 854,
        "2023": 900,
        "2024": 955,
        "2025": 1032
      },
      "山梨": {
        "2002": 647,
        "2003": 647,
        "2004": 648,
        "2005": 651,
        "2006": 655,
        "2007": 665,
        "2008": 676,
        "2009": 677,
        "2010": 689,
        "2011": 690,
        "2012": 695,
        "2013": 706,
        "2014": 721,
        "2015": 737,
        "2016": 759,
        "2017": 784,
        "2018": 810,
        "2019": 837,
        "2020": 838,
        "2021": 866,
        "2022": 898,
        "2023": 938,
        "2024": 988,
        "2025": 1052
      },
      "岐阜": {
        "2002": 668,
        "2003": 668,
        "2004": 669,
        "2005": 671,
        "2006": 675,
        "2007": 685,
        "2008": 696,
        "2009": 696,
        "2010": 706,
        "2011": 707,
        "2012": 713,
        "2013": 724,
        "2014": 738,
        "2015": 754,
        "2016": 776,
        "2017": 800,
        "2018": 825,
        "2019": 851,
        "2020": 852,
        "2021": 880,
        "2022": 910,
        "2023": 950,
        "2024": 1001,
        "2025": 1065
      },
      "岡山": {
        "2002": 640,
        "2003": 640,
        "2004": 641,
        "2005": 644,
        "2006": 648,
        "2007": 658,
        "2008": 669,
        "2009": 670,
        "2010": 683,
        "2011": 685,
        "2012": 691,
        "2013": 703,
        "2014": 719,
        "2015": 735,
        "2016": 757,
        "2017": 781,
        "2018": 807,
        "2019": 833,
        "2020": 834,
        "2021": 862,
        "2022": 892,
        "2023": 932,
        "2024": 982,
        "2025": 1047
      },
      "岩手": {
        "2002": 605,
        "2003": 605,
        "2004": 606,
        "2005": 608,
        "2006": 610,
        "2007": 619,
        "2008": 628,
        "2009": 631,
        "2010": 644,
        "2011": 645,
        "2012": 653,
        "2013": 665,
        "2014": 678,
        "2015": 695,
        "2016": 716,
        "2017": 738,
        "2018": 762,
        "2019": 790,
        "2020": 793,
        "2021": 821,
        "2022": 854,
        "2023": 893,
        "2024": 952,
        "2025": 1031
      },
      "島根": {
        "2002": 609,
        "2003": 609,
        "2004": 610,
        "2005": 612,
        "2006": 614,
        "2007": 621,
        "2008": 629,
        "2009": 630,
        "2010": 642,
        "2011": 646,
        "2012": 652,
        "2013": 664,
        "2014": 679,
        "2015": 696,
        "2016": 718,
        "2017": 740,
        "2018": 764,
        "2019": 790,
        "2020": 792,
        "2021": 824,
        "2022": 857,
        "2023": 904,
        "2024": 962,
        "2025": 1033
      },
      "広島": {
        "2002": 644,
        "2003": 644,
        "2004": 645,
        "2005": 649,
        "2006": 654,
        "2007": 669,
        "2008": 683,
        "2009": 692,
        "2010": 704,
        "2011": 710,
        "2012": 719,
        "2013": 733,
        "2014": 750,
        "2015": 769,
        "2016": 793,
        "2017": 818,
        "2018": 844,
        "2019": 871,
        "2020": 871,
        "2021": 899,
        "2022": 930,
        "2023": 970,
        "2024": 1020,
        "2025": 1085
      },
      "徳島": {
        "2002": 611,
        "2003": 611,
        "2004": 612,
        "2005": 615,
        "2006": 617,
        "2007": 625,
        "2008": 632,
        "2009": 633,
        "2010": 645,
        "2011": 647,
        "2012": 654,
        "2013": 666,
        "2014": 679,
        "2015": 695,
        "2016": 716,
        "2017": 740,
        "2018": 766,
        "2019": 793,
        "2020": 796,
        "2021": 824,
        "2022": 855,
        "2023": 896,
        "2024": 980,
        "2025": 1046
      },
      "愛媛": {
        "2002": 611,
        "2003": 611,
        "2004": 612,
        "2005": 614,
        "2006": 616,
        "2007": 623,
        "2008": 631,
        "2009": 632,
        "2010": 644,
        "2011": 647,
        "2012": 654,
        "2013": 666,
        "2014": 680,
        "2015": 696,
        "2016": 717,
        "2017": 739,
        "2018": 764,
        "2019": 790,
        "2020": 793,
        "2021": 821,
        "2022": 853,
        "2023": 897,
        "2024": 956,
        "2025": 1033
      },
      "愛知": {
        "2002": 681,
        "2003": 681,
        "2004": 683,
        "2005": 688,
        "2006": 694,
        "2007": 714,
        "2008": 731,
        "2009": 732,
        "2010": 745,
        "2011": 750,
        "2012": 758,
        "2013": 780,
        "2014": 800,
        "2015": 820,
        "2016": 845,
        "2017": 871,
        "2018": 898,
        "2019": 926,
        "2020": 927,
        "2021": 955,
        "2022": 986,
        "2023": 1027,
        "2024": 1077,
        "2025": 1140
      },
      "新潟": {
        "2002": 641,
        "2003": 641,
        "2004": 642,
        "2005": 645,
        "2006": 648,
        "2007": 657,
        "2008": 669,
        "2009": 669,
        "2010": 681,
        "2011": 683,
        "2012": 689,
        "2013": 701,
        "2014": 715,
        "2015": 731,
        "2016": 753,
        "2017": 778,
        "2018": 803,
        "2019": 830,
        "2020": 831,
        "2021": 859,
        "2022": 890,
        "2023": 931,
        "2024": 985,
        "2025": 1050
      },
      "東京": {
        "2002": 708,
        "2003": 708,
        "2004": 710,
        "2005": 714,
        "2006": 719,
        "2007": 739,
        "2008": 766,
        "2009": 791,
        "2010": 821,
        "2011": 837,
        "2012": 850,
        "2013": 869,
        "2014": 888,
        "2015": 907,
        "2016": 932,
        "2017": 958,
        "2018": 985,
        "2019": 1013,
        "2020": 1013,
        "2021": 1041,
        "2022": 1072,
        "2023": 1113,
        "2024": 1163,
        "2025": 1226
      },
      "栃木": {
        "2002": 648,
        "2003": 648,
        "2004": 649,
        "2005": 652,
        "2006": 657,
        "2007": 671,
        "2008": 683,
        "2009": 685,
        "2010": 697,
        "2011": 700,
        "2012": 705,
        "2013": 718,
        "2014": 733,
        "2015": 751,
        "2016": 775,
        "2017": 800,
        "2018": 826,
        "2019": 853,
        "2020": 854,
        "2021": 882,
        "2022": 913,
        "2023": 954,
        "2024": 1004,
        "2025": 1068
      },
      "沖縄": {
        "2002": 604,
        "2003": 605,
        "2004": 606,
        "2005": 608,
        "2006": 610,
        "2007": 618,
        "2008": 627,
        "2009": 629,
        "2010": 642,
        "2011": 645,
        "2012": 653,
        "2013": 664,
        "2014": 677,
        "2015": 693,
        "2016": 714,
        "2017": 737,
        "2018": 762,
        "2019": 790,
        "2020": 792,
        "2021": 820,
        "2022": 853,
        "2023": 896,
        "2024": 952,
        "2025": 1023
      },
      "滋賀": {
        "2002": 651,
        "2003": 651,
        "2004": 652,
        "2005": 657,
        "2006": 662,
        "2007": 677,
        "2008": 691,
        "2009": 693,
        "2010": 706,
        "2011": 709,
        "2012": 716,
        "2013": 730,
        "2014": 746,
        "2015": 764,
        "2016": 788,
        "2017": 813,
        "2018": 839,
        "2019": 866,
        "2020": 868,
        "2021": 896,
        "2022": 927,
        "2023": 967,
        "2024": 1017,
        "2025": 1080
      },
      "熊本": {
        "2002": 606,
        "2003": 606,
        "2004": 607,
        "2005": 609,
        "2006": 612,
        "2007": 620,
        "2008": 628,
        "2009": 630,
        "2010": 643,
        "2011": 647,
        "2012": 653,
        "2013": 664,
        "2014": 677,
        "2015": 694,
        "2016": 715,
        "2017": 737,
        "2018": 762,
        "2019": 790,
        "2020": 793,
        "2021": 821,
        "2022": 853,
        "2023": 898,
        "2024": 952,
        "2025": 1034
      },
      "石川": {
        "2002": 645,
        "2003": 645,
        "2004": 646,
        "2005": 649,
        "2006": 652,
        "2007": 662,
        "2008": 673,
        "2009": 674,
        "2010": 686,
        "2011": 687,
        "2012": 693,
        "2013": 704,
        "2014": 718,
        "2015": 735,
        "2016": 757,
        "2017": 781,
        "2018": 806,
        "2019": 832,
        "2020": 833,
        "2021": 861,
        "2022": 891,
        "2023": 933,
        "2024": 984,
        "2025": 1054
      },
      "神奈川": {
        "2002": 706,
        "2003": 707,
        "2004": 708,
        "2005": 712,
        "2006": 717,
        "2007": 736,
        "2008": 766,
        "2009": 789,
        "2010": 818,
        "2011": 836,
        "2012": 849,
        "2013": 868,
        "2014": 887,
        "2015": 905,
        "2016": 930,
        "2017": 956,
        "2018": 983,
        "2019": 1011,
        "2020": 1012,
        "2021": 1040,
        "2022": 1071,
        "2023": 1112,
        "2024": 1162,
        "2025": 1225
      },
      "福井": {
        "2002": 642,
        "2003": 642,
        "2004": 643,
        "2005": 645,
        "2006": 649,
        "2007": 659,
        "2008": 670,
        "2009": 671,
        "2010": 683,
        "2011": 684,
        "2012": 690,
        "2013": 701,
        "2014": 716,
        "2015": 732,
        "2016": 754,
        "2017": 778,
        "2018": 803,
        "2019": 829,
        "2020": 830,
        "2021": 858,
        "2022": 888,
        "2023": 931,
        "2024": 984,
        "2025": 1053
      },
      "福岡": {
        "2002": 643,
        "2003": 644,
        "2004": 645,
        "2005": 648,
        "2006": 652,
        "2007": 663,
        "2008": 675,
        "2009": 680,
        "2010": 692,
        "2011": 695,
        "2012": 701,
        "2013": 712,
        "2014": 727,
        "2015": 743,
        "2016": 765,
        "2017": 789,
        "2018": 814,
        "2019": 841,
        "2020": 842,
        "2021": 870,
        "2022": 900,
        "2023": 941,
        "2024": 992,
        "2025": 1057
      },
      "福島": {
        "2002": 610,
        "2003": 610,
        "2004": 611,
        "2005": 614,
        "2006": 618,
        "2007": 629,
        "2008": 641,
        "2009": 644,
        "2010": 657,
        "2011": 658,
        "2012": 664,
        "2013": 675,
        "2014": 689,
        "2015": 705,
        "2016": 726,
        "2017": 748,
        "2018": 772,
        "2019": 798,
        "2020": 800,
        "2021": 828,
        "2022": 858,
        "2023": 900,
        "2024": 955,
        "2025": 1033
      },
      "秋田": {
        "2002": 605,
        "2003": 605,
        "2004": 606,
        "2005": 608,
        "2006": 610,
        "2007": 618,
        "2008": 629,
        "2009": 632,
        "2010": 645,
        "2011": 647,
        "2012": 654,
        "2013": 665,
        "2014": 679,
        "2015": 695,
        "2016": 716,
        "2017": 738,
        "2018": 762,
        "2019": 790,
        "2020": 792,
        "2021": 822,
        "2022": 853,
        "2023": 897,
        "2024": 951,
        "2025": 1031
      },
      "群馬": {
        "2002": 644,
        "2003": 644,
        "2004": 645,
        "2005": 649,
        "2006": 654,
        "2007": 664,
        "2008": 675,
        "2009": 676,
        "2010": 688,
        "2011": 690,
        "2012": 696,
        "2013": 707,
        "2014": 721,
        "2015": 737,
        "2016": 759,
        "2017": 783,
        "2018": 809,
        "2019": 835,
        "2020": 837,
        "2021": 865,
        "2022": 895,
        "2023": 935,
        "2024": 985,
        "2025": 1063
      },
      "茨城": {
        "2002": 647,
        "2003": 647,
        "2004": 648,
        "2005": 651,
        "2006": 655,
        "2007": 665,
        "2008": 676,
        "2009": 678,
        "2010": 690,
        "2011": 692,
        "2012": 699,
        "2013": 713,
        "2014": 729,
        "2015": 747,
        "2016": 771,
        "2017": 796,
        "2018": 822,
        "2019": 849,
        "2020": 851,
        "2021": 879,
        "2022": 911,
        "2023": 953,
        "2024": 1005,
        "2025": 1074
      },
      "長崎": {
        "2002": 605,
        "2003": 605,
        "2004": 606,
        "2005": 608,
        "2006": 611,
        "2007": 619,
        "2008": 628,
        "2009": 629,
        "2010": 642,
        "2011": 646,
        "2012": 653,
        "2013": 664,
        "2014": 677,
        "2015": 694,
        "2016": 715,
        "2017": 737,
        "2018": 762,
        "2019": 790,
        "2020": 793,
        "2021": 821,
        "2022": 853,
        "2023": 898,
        "2024": 953,
        "2025": 1031
      },
      "長野": {
        "2002": 646,
        "2003": 646,
        "2004": 647,
        "2005": 650,
        "2006": 655,
        "2007": 669,
        "2008": 680,
        "2009": 681,
        "2010": 693,
        "2011": 694,
        "2012": 700,
        "2013": 713,
        "2014": 728,
        "2015": 746,
        "2016": 770,
        "2017": 795,
        "2018": 821,
        "2019": 848,
        "2020": 849,
        "2021": 877,
        "2022": 908,
        "2023": 948,
        "2024": 998,
        "2025": 1061
      },
      "青森": {
        "2002": 605,
        "2003": 605,
        "2004": 606,
        "2005": 608,
        "2006": 610,
        "2007": 619,
        "2008": 630,
        "2009": 633,
        "2010": 645,
        "2011": 647,
        "2012": 654,
        "2013": 665,
        "2014": 679,
        "2015": 695,
        "2016": 716,
        "2017": 738,
        "2018": 762,
        "2019": 790,
        "2020": 793,
        "2021": 822,
        "2022": 853,
        "2023": 898,
        "2024": 953,
        "2025": 1029
      },
      "静岡": {
        "2002": 671,
        "2003": 671,
        "2004": 673,
        "2005": 677,
        "2006": 682,
        "2007": 697,
        "2008": 711,
        "2009": 713,
        "2010": 725,
        "2011": 728,
        "2012": 735,
        "2013": 749,
        "2014": 765,
        "2015": 783,
        "2016": 807,
        "2017": 832,
        "2018": 858,
        "2019": 885,
        "2020": 885,
        "2021": 913,
        "2022": 944,
        "2023": 984,
        "2024": 1034,
        "2025": 1097
      },
      "香川": {
        "2002": 618,
        "2003": 619,
        "2004": 620,
        "2005": 625,
        "2006": 629,
        "2007": 640,
        "2008": 651,
        "2009": 652,
        "2010": 664,
        "2011": 667,
        "2012": 674,
        "2013": 686,
        "2014": 702,
        "2015": 719,
        "2016": 742,
        "2017": 766,
        "2018": 792,
        "2019": 818,
        "2020": 820,
        "2021": 848,
        "2022": 878,
        "2023": 918,
        "2024": 970,
        "2025": 1036
      },
      "高知": {
        "2002": 611,
        "2003": 611,
        "2004": 611,
        "2005": 613,
        "2006": 615,
        "2007": 622,
        "2008": 630,
        "2009": 631,
        "2010": 642,
        "2011": 645,
        "2012": 652,
        "2013": 664,
        "2014": 677,
        "2015": 693,
        "2016": 715,
        "2017": 737,
        "2018": 762,
        "2019": 790,
        "2020": 792,
        "2021": 820,
        "2022": 853,
        "2023": 897,
        "2024": 952,
        "2025": 1023
      },
      "鳥取": {
        "2002": 610,
        "2003": 610,
        "2004": 611,
        "2005": 612,
        "2006": 614,
        "2007": 621,
        "2008": 629,
        "2009": 630,
        "2010": 642,
        "2011": 646,
        "2012": 653,
        "2013": 664,
        "2014": 677,
        "2015": 693,
        "2016": 715,
        "2017": 738,
        "2018": 762,
        "2019": 790,
        "2020": 792,
        "2021": 821,
        "2022": 854,
        "2023": 900,
        "2024": 957,
        "2025": 1030
      },
      "鹿児島": {
        "2002": 605,
        "2003": 605,
        "2004": 606,
        "2005": 608,
        "2006": 611,
        "2007": 619,
        "2008": 627,
        "2009": 630,
        "2010": 642,
        "2011": 647,
        "2012": 654,
        "2013": 665,
        "2014": 678,
        "2015": 694,
        "2016": 715,
        "2017": 737,
        "2018": 761,
        "2019": 790,
        "2020": 793,
        "2021": 821,
        "2022": 853,
        "2023": 897,
        "2024": 953,
        "2025": 1026
      }
    },
    "min_wage_history_by_pref_source": "transcribed_from_uploaded_excel_001571219 (1).xlsx_sheet_H14～R７_amount_columns"
  },
  "prefs": {
    "北海道": {
      "cpi_yoy": null,
      "cpi_asof": null,
      "wage_yoy": null,
      "wage_asof": null
    },
    "青森": {
      "cpi_yoy": null,
      "cpi_asof": null,
      "wage_yoy": null,
      "wage_asof": null
    },
    "岩手": {
      "cpi_yoy": null,
      "cpi_asof": null,
      "wage_yoy": null,
      "wage_asof": null
    },
    "宮城": {
      "cpi_yoy": null,
      "cpi_asof": null,
      "wage_yoy": null,
      "wage_asof": null
    },
    "秋田": {
      "cpi_yoy": null,
      "cpi_asof": null,
      "wage_yoy": null,
      "wage_asof": null
    },
    "山形": {
      "cpi_yoy": null,
      "cpi_asof": null,
      "wage_yoy": null,
      "wage_asof": null
    },
    "福島": {
      "cpi_yoy": null,
      "cpi_asof": null,
      "wage_yoy": null,
      "wage_asof": null
    },
    "茨城": {
      "cpi_yoy": null,
      "cpi_asof": null,
      "wage_yoy": null,
      "wage_asof": null
    },
    "栃木": {
      "cpi_yoy": null,
      "cpi_asof": null,
      "wage_yoy": null,
      "wage_asof": null
    },
    "群馬": {
      "cpi_yoy": null,
      "cpi_asof": null,
      "wage_yoy": null,
      "wage_asof": null
    },
    "埼玉": {
      "cpi_yoy": null,
      "cpi_asof": null,
      "wage_yoy": null,
      "wage_asof": null
    },
    "千葉": {
      "cpi_yoy": null,
      "cpi_asof": null,
      "wage_yoy": null,
      "wage_asof": null
    },
    "東京": {
      "cpi_yoy": null,
      "cpi_asof": null,
      "wage_yoy": null,
      "wage_asof": null
    },
    "神奈川": {
      "cpi_yoy": null,
      "cpi_asof": null,
      "wage_yoy": null,
      "wage_asof": null
    },
    "新潟": {
      "cpi_yoy": null,
      "cpi_asof": null,
      "wage_yoy": null,
      "wage_asof": null
    },
    "富山": {
      "cpi_yoy": null,
      "cpi_asof": null,
      "wage_yoy": null,
      "wage_asof": null
    },
    "石川": {
      "cpi_yoy": null,
      "cpi_asof": null,
      "wage_yoy": null,
      "wage_asof": null
    },
    "福井": {
      "cpi_yoy": null,
      "cpi_asof": null,
      "wage_yoy": null,
      "wage_asof": null
    },
    "山梨": {
      "cpi_yoy": null,
      "cpi_asof": null,
      "wage_yoy": null,
      "wage_asof": null
    },
    "長野": {
      "cpi_yoy": null,
      "cpi_asof": null,
      "wage_yoy": null,
      "wage_asof": null
    },
    "岐阜": {
      "cpi_yoy": null,
      "cpi_asof": null,
      "wage_yoy": null,
      "wage_asof": null
    },
    "静岡": {
      "cpi_yoy": null,
      "cpi_asof": null,
      "wage_yoy": null,
      "wage_asof": null
    },
    "愛知": {
      "cpi_yoy": null,
      "cpi_asof": null,
      "wage_yoy": null,
      "wage_asof": null
    },
    "三重": {
      "cpi_yoy": null,
      "cpi_asof": null,
      "wage_yoy": null,
      "wage_asof": null
    },
    "滋賀": {
      "cpi_yoy": null,
      "cpi_asof": null,
      "wage_yoy": null,
      "wage_asof": null
    },
    "京都": {
      "cpi_yoy": null,
      "cpi_asof": null,
      "wage_yoy": null,
      "wage_asof": null
    },
    "大阪": {
      "cpi_yoy": null,
      "cpi_asof": null,
      "wage_yoy": null,
      "wage_asof": null
    },
    "兵庫": {
      "cpi_yoy": null,
      "cpi_asof": null,
      "wage_yoy": null,
      "wage_asof": null
    },
    "奈良": {
      "cpi_yoy": null,
      "cpi_asof": null,
      "wage_yoy": null,
      "wage_asof": null
    },
    "和歌山": {
      "cpi_yoy": null,
      "cpi_asof": null,
      "wage_yoy": null,
      "wage_asof": null
    },
    "鳥取": {
      "cpi_yoy": null,
      "cpi_asof": null,
      "wage_yoy": null,
      "wage_asof": null
    },
    "島根": {
      "cpi_yoy": null,
      "cpi_asof": null,
      "wage_yoy": null,
      "wage_asof": null
    },
    "岡山": {
      "cpi_yoy": null,
      "cpi_asof": null,
      "wage_yoy": null,
      "wage_asof": null
    },
    "広島": {
      "cpi_yoy": null,
      "cpi_asof": null,
      "wage_yoy": null,
      "wage_asof": null
    },
    "山口": {
      "cpi_yoy": null,
      "cpi_asof": null,
      "wage_yoy": null,
      "wage_asof": null
    },
    "徳島": {
      "cpi_yoy": null,
      "cpi_asof": null,
      "wage_yoy": null,
      "wage_asof": null
    },
    "香川": {
      "cpi_yoy": null,
      "cpi_asof": null,
      "wage_yoy": null,
      "wage_asof": null
    },
    "愛媛": {
      "cpi_yoy": null,
      "cpi_asof": null,
      "wage_yoy": null,
      "wage_asof": null
    },
    "高知": {
      "cpi_yoy": null,
      "cpi_asof": null,
      "wage_yoy": null,
      "wage_asof": null
    },
    "福岡": {
      "cpi_yoy": null,
      "cpi_asof": null,
      "wage_yoy": null,
      "wage_asof": null
    },
    "佐賀": {
      "cpi_yoy": null,
      "cpi_asof": null,
      "wage_yoy": null,
      "wage_asof": null
    },
    "長崎": {
      "cpi_yoy": null,
      "cpi_asof": null,
      "wage_yoy": null,
      "wage_asof": null
    },
    "熊本": {
      "cpi_yoy": null,
      "cpi_asof": null,
      "wage_yoy": null,
      "wage_asof": null
    },
    "大分": {
      "cpi_yoy": null,
      "cpi_asof": null,
      "wage_yoy": null,
      "wage_asof": null
    },
    "宮崎": {
      "cpi_yoy": null,
      "cpi_asof": null,
      "wage_yoy": null,
      "wage_asof": null
    },
    "鹿児島": {
      "cpi_yoy": null,
      "cpi_asof": null,
      "wage_yoy": null,
      "wage_asof": null
    },
    "沖縄": {
      "cpi_yoy": null,
      "cpi_asof": null,
      "wage_yoy": null,
      "wage_asof": null
    }
  }
}
